solaredge_setapp/__init__.py
solaredge_setapp/information.py
solaredge_setapp/information_pb2.py
solaredge_setapp/maintenance.py
solaredge_setapp/maintenance_pb2.py
solaredge_setapp/status.py
solaredge_setapp/status_pb2.py
solaredge_setapp-0.1.5.dist-info/LICENSE
solaredge_setapp-0.1.5.dist-info/METADATA
solaredge_setapp-0.1.5.dist-info/WHEEL
solaredge_setapp-0.1.5.dist-info/top_level.txt
solaredge_setapp-0.1.5.dist-info/RECORD
