Metadata-Version: 2.1
Name: solaredge-setapp
Version: 0.1.5
Summary: SolarEdge SetApp protocol buffers parser library
Home-page: https://github.com/nmakel/solaredge_setapp
Author: nmakel
Author-email: 
License: MIT License
Platform: UNKNOWN
Classifier: Development Status :: 4 - Beta
Classifier: Programming Language :: Python :: 3.7
Classifier: Operating System :: OS Independent
Classifier: Environment :: Console
Classifier: Natural Language :: English
Classifier: Intended Audience :: Developers
Classifier: License :: OSI Approved :: MIT License
Requires-Dist: protobuf (>=3.6.1)
Requires-Dist: requests (>=2.12.4)
